wirecloud/__init__.py
wirecloud/keycloak/__init__.py
wirecloud/keycloak/models.py
wirecloud/keycloak/plugins.py
wirecloud/keycloak/proxy.py
wirecloud/keycloak/social_auth_backend.py
wirecloud/keycloak/urls.py
wirecloud/keycloak/utils.py
wirecloud/keycloak/views.py
wirecloud/keycloak/static/js/keycloak/sso.js
wirecloud/keycloak/tests/__init__.py
wirecloud/keycloak/tests/plugins.py
wirecloud/keycloak/tests/proxy.py
wirecloud/keycloak/tests/social_backend.py
wirecloud/keycloak/tests/tests.py
wirecloud/keycloak/tests/utils.py
wirecloud/keycloak/tests/views.py
wirecloud_keycloak-0.4.5.dist-info/METADATA
wirecloud_keycloak-0.4.5.dist-info/WHEEL
wirecloud_keycloak-0.4.5.dist-info/top_level.txt
wirecloud_keycloak-0.4.5.dist-info/RECORD
