Metadata-Version: 2.1
Name: wirecloud-keycloak
Version: 0.4.5
Summary: WireCloud extension supporting authentication with Keycloak IDM
Home-page: https://github.com/Ficodes/wirecloud-keycloak
Author: FICODES
Author-email: contact@ficodes.com
License: AGPLv3+
Platform: UNKNOWN
Classifier: Programming Language :: Python :: 3
Classifier: License :: OSI Approved :: GNU Affero General Public License v3 or later (AGPLv3+)
Classifier: Operating System :: OS Independent
Requires-Dist: wirecloud (<1.5,>=1.2.0)
Requires-Dist: social-auth-core[openidconnect] (<5.0.0)
Requires-Dist: social-auth-app-django (<6.0.0)
